tools/__init__.py
tools/tools.py
jaysun_tools-1.0.0.dist-info/LICENSE
jaysun_tools-1.0.0.dist-info/METADATA
jaysun_tools-1.0.0.dist-info/WHEEL
jaysun_tools-1.0.0.dist-info/top_level.txt
jaysun_tools-1.0.0.dist-info/RECORD
