Metadata-Version: 2.1
Name: jaysun-tools
Version: 1.0.0
Summary: pypi测试
Home-page: https://github.com/test
Author: jaysun
Author-email: jaysun1015@outlook.com
License: MIT
Classifier: License :: OSI Approved :: MIT License
Classifier: Operating System :: OS Independent
Classifier: Programming Language :: Python :: 3
Requires-Python: >=3.79
License-File: LICENSE
Requires-Dist: PyYAML ==6.0
Requires-Dist: Requests ==2.31.0
Requires-Dist: setuptools ==67.3.3
